auto_commenter/__init__.py
auto_commenter/__main__.py
auto_commenter/code_analyzer.py
auto_commenter/comment_generator.py
auto_commenter/docstring_formatters.py
auto_commenter/utils.py
auto_commenter-0.1.0.dist-info/METADATA
auto_commenter-0.1.0.dist-info/WHEEL
auto_commenter-0.1.0.dist-info/top_level.txt
auto_commenter-0.1.0.dist-info/RECORD
