Metadata-Version: 2.4
Name: auto-commenter
Version: 0.1.0
Summary: A Python package for automatically generating docstrings based on function arguments and return types.
Home-page: https://github.com/Dinesh123527/auto-commenter
Author: veganapa
Author-email: varmadinesh249@gmail.com
Classifier: Programming Language :: Python :: 3
Classifier: License :: OSI Approved :: MIT License
Classifier: Operating System :: OS Independent
Requires-Python: >=3.6
Requires-Dist: numpy
Requires-Dist: pandas
Dynamic: author
Dynamic: author-email
Dynamic: classifier
Dynamic: description
Dynamic: description-content-type
Dynamic: home-page
Dynamic: requires-dist
Dynamic: requires-python
Dynamic: summary
